qi-3.1.5.dist-info/METADATA
qi-3.1.5.dist-info/WHEEL
qi-3.1.5.dist-info/RECORD
qi-3.1.5.dist-info/licenses/COPYING
qi.libs/libboost_date_time-f4ce6fbe.so.1.83.0
qi.libs/libqi-df5eed93.so.4.0.5
qi.libs/libboost_filesystem-dd63639a.so.1.83.0
qi.libs/libboost_locale-4a15d579.so.1.83.0
qi.libs/libboost_random-d7d6751c.so.1.83.0
qi.libs/libssl-839bd816.so.3
qi.libs/libboost_chrono-9707120a.so.1.83.0
qi.libs/libcrypto-14838552.so.3
qi.libs/libboost_program_options-ee423e53.so.1.83.0
qi.libs/libboost_thread-205ac081.so.1.83.0
qi.libs/libboost_regex-11696d99.so.1.83.0
qi.libs/libboost_atomic-0df6d513.so.1.83.0
qi.libs/libboost_container-59dbc684.so.1.83.0
qi/_binder.py
qi/_type.py
qi/path.py
qi/translator.py
qi/native.py
qi/qi_python.so
qi/_version.py
qi/logging.py
qi/__init__.py
