Metadata-Version: 2.1
Name: qi
Version: 3.1.5
Summary: LibQi Python bindings
Keywords: libqi,qi,naoqi,aldebaran,robotics,robot,nao,pepper,romeo,plato
Maintainer-Email: Unknown <framework@aldebaran.com>, Vincent Palancher <vincent.palancher@aldebaran.com>, =?utf-8?b?SsOpcsOpbXkgTW9ubm9u?= <jmonnon@aldebaran.com>
License: Copyright (c) 2011-2020, Softbank Robotics Europe
Classifier: Development Status :: 5 - Production/Stable
Classifier: License :: OSI Approved :: BSD License
Classifier: Intended Audience :: Developers
Classifier: Topic :: Software Development :: Libraries
Classifier: Topic :: Software Development :: Libraries :: Application Frameworks
Classifier: Topic :: Software Development :: Embedded Systems
Classifier: Framework :: Robot Framework :: Library
Classifier: Programming Language :: Python :: 3
Classifier: Programming Language :: Python :: 3.7
Classifier: Programming Language :: Python :: 3.8
Classifier: Programming Language :: Python :: 3.9
Classifier: Programming Language :: Python :: 3.10
Classifier: Programming Language :: Python :: 3.11
Classifier: Programming Language :: Python :: 3 :: Only
Project-URL: Repository, https://github.com/aldebaran/libqi-python
Requires-Python: >=3.7
